hecdbetz/__init__.py
hecdbetz/add_num.py
hecdbetz/calculate.py
hecdbetz-5.0.dist-info/entry_points.txt
hecdbetz-5.0.dist-info/LICENSE
hecdbetz-5.0.dist-info/WHEEL
hecdbetz-5.0.dist-info/METADATA
hecdbetz-5.0.dist-info/RECORD
